atlas/__init__.py
atlas/content_index.py
atlas/content_parser.py
atlas/run_atlas.py
atlas/settings.py
atila_atlas-0.0.2.dist-info/LICENSE.txt
atila_atlas-0.0.2.dist-info/METADATA
atila_atlas-0.0.2.dist-info/WHEEL
atila_atlas-0.0.2.dist-info/entry_points.txt
atila_atlas-0.0.2.dist-info/top_level.txt
atila_atlas-0.0.2.dist-info/RECORD
