Metadata-Version: 2.1
Name: atila-atlas
Version: 0.0.2
Summary: Atlas is a search engine for parsing a collection of web pages and making it searchable.
Home-page: https://github.com/atilatech/atlas
Author: Atila Tech
Author-email: info@atila.ca
License: MIT
Project-URL: Bug Tracker, https://github.com/atilatech/atlas/issues
Platform: UNKNOWN
Requires-Python: >=3.6
License-File: LICENSE.txt
Requires-Dist: algoliasearch (==2.6.1)
Requires-Dist: beautifulsoup4 (==4.10.0)
Requires-Dist: docopt (==0.6.2)
Requires-Dist: publicsuffix2 (==2.20191221)
Requires-Dist: requests (==2.27.1)
